odoo/addons/purchase_stock_budget_plan_detail/README.rst
odoo/addons/purchase_stock_budget_plan_detail/__init__.py
odoo/addons/purchase_stock_budget_plan_detail/__manifest__.py
odoo/addons/purchase_stock_budget_plan_detail/models/__init__.py
odoo/addons/purchase_stock_budget_plan_detail/models/purchase_order_line.py
odoo/addons/purchase_stock_budget_plan_detail/readme/CONTRIBUTORS.md
odoo/addons/purchase_stock_budget_plan_detail/readme/DESCRIPTION.md
odoo/addons/purchase_stock_budget_plan_detail/static/description/icon.png
odoo/addons/purchase_stock_budget_plan_detail/static/description/index.html
odoo/addons/purchase_stock_budget_plan_detail/tests/__init__.py
odoo/addons/purchase_stock_budget_plan_detail/tests/test_purchase_stock_budget_plan_detail.py
odoo_addon_purchase_stock_budget_plan_detail-18.0.1.0.0.1.dist-info/METADATA
odoo_addon_purchase_stock_budget_plan_detail-18.0.1.0.0.1.dist-info/WHEEL
odoo_addon_purchase_stock_budget_plan_detail-18.0.1.0.0.1.dist-info/top_level.txt
odoo_addon_purchase_stock_budget_plan_detail-18.0.1.0.0.1.dist-info/RECORD
